sysplant/__init__.py
sysplant/abstracts/__init__.py
sysplant/abstracts/abstractFactory.py
sysplant/abstracts/abstractGenerator.py
sysplant/constants/__init__.py
sysplant/constants/sysplantConstants.py
sysplant/data/__init__.py
sysplant/data/definitions.json
sysplant/data/prototypes.json
sysplant/data/windef.nim
sysplant/managers/__init__.py
sysplant/managers/cGenerator.py
sysplant/managers/nimGenerator.py
sysplant/managers/templateManager.py
sysplant/sysplant.py
sysplant/templates/__init__.py
sysplant/templates/base.c
sysplant/templates/base.nim
sysplant/templates/iterators/__init__.py
sysplant/templates/iterators/canterlot.c
sysplant/templates/iterators/canterlot.nim
sysplant/templates/iterators/freshy.c
sysplant/templates/iterators/freshy.nim
sysplant/templates/iterators/halo.c
sysplant/templates/iterators/halo.nim
sysplant/templates/iterators/hell.c
sysplant/templates/iterators/hell.nim
sysplant/templates/iterators/syswhispers.c
sysplant/templates/iterators/syswhispers.nim
sysplant/templates/iterators/syswhispers3.c
sysplant/templates/iterators/syswhispers3.nim
sysplant/templates/iterators/tartarus.c
sysplant/templates/iterators/tartarus.nim
sysplant/templates/resolvers/__init__.py
sysplant/templates/resolvers/basic.c
sysplant/templates/resolvers/basic.nim
sysplant/templates/resolvers/number.c
sysplant/templates/resolvers/number.nim
sysplant/templates/resolvers/random.c
sysplant/templates/resolvers/random.nim
sysplant/templates/stubs/__init__.py
sysplant/templates/stubs/direct_x64.c
sysplant/templates/stubs/direct_x64.nim
sysplant/templates/stubs/direct_x86.c
sysplant/templates/stubs/direct_x86.nim
sysplant/templates/stubs/indirect_x64.c
sysplant/templates/stubs/indirect_x64.nim
sysplant/templates/stubs/random_x64.c
sysplant/templates/stubs/random_x64.nim
sysplant/utils/__init__.py
sysplant/utils/loggerSingleton.py
sysplant/utils/singleton.py
sysplant-0.3.1.dist-info/LICENSE
sysplant-0.3.1.dist-info/METADATA
sysplant-0.3.1.dist-info/WHEEL
sysplant-0.3.1.dist-info/RECORD
